Workbook

Sheet Income Statement
A1: BASF — Income Statement (FY2021–FY2025)
A2: Revenue | B2: 78598 | C2: 87327 | D2: 68902 | E2: 61444 | F2: 59657
A3: Revenue Growth | B3: 0.3288 | C3: 0.1111 | D3: -0.211 | E3: -0.1082 | F3: -0.0291
A4: Cost of Revenue | B4: 59091 | C4: 66697 | D4: 52506 | E4: 46534 | F4: 45527
A5: Gross Profit | B5: 19507 | C5: 20630 | D5: 16396 | E5: 14910 | F5: 14130
A6: Selling, General & Admin | B6: 9902 | C6: 11201 | D6: 10379 | E6: 9025 | F6: 8883
A7: Research & Development | B7: 2216 | C7: 2298 | D7: 2130 | E7: 1969 | F7: 1995
A8: Other Operating Expenses | B8: -115 | C8: 275 | D8: 1046 | E8: 1432 | F8: 779
A9: Operating Expenses | B9: 12040 | C9: 13774 | D9: 13555 | E9: 12426 | F9: 11657
A10: Operating Income | B10: 7467 | C10: 6856 | D10: 2841 | E10: 2484 | F10: 2473
A11: Interest Expense | B11: -506 | C11: -631 | D11: -868 | E11: -929 | F11: -924
A12: Interest & Investment Income | B12: 257 | C12: 354 | D12: 453 | E12: 512 | F12: 406
A13: Earnings From Equity Investments | B13: 960 | C13: -4499 | D13: 78 | E13: 653 | F13: 1055
... A19: Gain (Loss) on Sale of Assets | B19: 129 | C19: 250 | D19: 43 | E19: 65 | F19: 668
A20: Asset Writedown | B20: -103 | C20: -375 | D20: 6 | E20: - | F20: 8
A21: Pretax Income | B21: 7448 | C21: 1190 | D21: 1420 | E21: 1861 | F21: 2448
A22: Income Tax Expense | B22: 1430 | C22: 1581 | D22: 1041 | E22: 573 | F22: 907
A23: Earnings From Continuing Operations | B23: 6018 | C23: -391 | D23: 379 | E23: 1288 | F23: 1541
A24: Earnings From Discontinued Operations | B24: -36 | C24: - | D24: - | E24: 165 | F24: 185
A25: Net Income to Company | B25: 5982 | C25: -391 | D25: 379 | E25: 1453 | F25: 1726
A26: Minority Interest in Earnings | B26: -459 | C26: -236 | D26: -154 | E26: -155 | F26: -107
A27: Net Income | B27: 5523 | C27: -627 | D27: 225 | E27: 1298 | F27: 1619
A28: Net Income to Common | B28: 5523 | C28: -627 | D28: 225 | E28: 1298 | F28: 1619
A29: Net Income Growth | B29: - | C29: - | D29: - | E29: 4.7689 | F29: 0.2473
A30: Shares Outstanding (Basic) | B30: 918 | C30: 902 | D30: 893 | E30: 893 | F30: 892
A31: Shares Outstanding (Diluted) | B31: 920 | C31: 902 | D31: 895 | E31: 895 | F31: 894
A32: Shares Change | B32: 0.0003 | C32: -0.0204 | D32: -0.0074 | E32: -0.0001 | F32: -0.001
A33: EPS (Basic) | B33: 6.01 | C33: -0.7 | D33: 0.25 | E33: 1.45 | F33: 1.82
A34: EPS (Diluted) | B34: 6 | C34: -0.7 | D34: 0.25 | E34: 1.45 | F34: 1.81
A35: EPS Growth | B35: - | C35: - | D35: - | E35: 4.8 | F35: 0.2483

Sheet Balance Sheet
A1: BASF — Balance Sheet (FY2021–FY2025)
A2: Fiscal Year | B2: FY 2021 | C2: FY 2022 | D2: FY 2023 | E2: FY 2024 | F2: FY 2025
A3: Cash & Equivalents | B3: 2624 | C3: 2516 | D3: 2624 | E3: 2914 | F3: 2670
A4: Short-Term Investments | B4: 208 | C4: 232 | D4: 53 | E4: 67 | F4: 89
A5: Trading Asset Securities | B5: 1554 | C5: 1939 | D5: 1139 | E5: - | F5: 1327
A6: Cash & Short-Term Investments | B6: 4386 | C6: 4687 | D6: 3816 | E6: 2981 | F6: 4086
A7: Cash Growth | B7: -0.2858 | C7: 0.0686 | D7: -0.1858 | E7: -0.2188 | F7: 0.3707
A8: Accounts Receivable | B8: 11946 | C8: 12057 | D8: 10417 | E8: 10393 | F8: 8327
A9: Other Receivables | B9: 2187 | C9: 2485 | D9: 1761 | E9: 3996 | F9: 1623
A10: Receivables | B10: 14282 | C10: 14645 | D10: 12360 | E10: 14389 | F10: 10088
A11: Inventory | B11: 13868 | C11: 16028 | D11: 13876 | E11: 13681 | F11: 12168
A12: Prepaid Expenses | B12: 327 | C12: 285 | D12: 225 | E12: - | F12: 207
A13: Other Current Assets | B13: 2188 | C13: 1777 | D13: 1195 | E13: 181 | F13: 5135
A14: Total Current Assets | B14: 35051 | C14: 37422 | D14: 31472 | E14: 31232 | F14: 31684
A15: Property, Plant & Equipment | B15: 17871 | C15: 17908 | D15: 17639 | E15: 17773 | F15: 20325
A16: Long-Term Investments | B16: 12958 | C16: 8121 | D16: 7671 | E16: 6975 | F16: 6048
A17: Goodwill | B17: 7521 | C17: 7695 | D17: 7499 | E17: 7720 | F17: 6553
A18: Other Intangible Assets | B18: 5978 | C18: 5578 | D18: 4717 | E18: 4263 | F18: 3139
A19: Long-Term Accounts Receivable | B19: 40 | C19: 32 | D19: 30 | E19: 29 | F19: 27
A20: Long-Term Deferred Tax Assets | B20: 2600 | C20: 880 | D20: 617 | E20: 574 | F20: 544
A21: Other Long-Term Assets | B21: 5322 | C21: 6791 | D21: 7693 | E21: 11797 | F21: 7834
A22: Total Assets | B22: 87383 | C22: 84472 | D22: 77395 | E22: 80415 | F22: 76174
A24: Average Accounts Receivable | C24: =(B8+C8)/2 -> 12001.5 | D24: =(C8+D8)/2 -> 11237 | E24: =(D8+E8)/2 -> 10405 | F24: =(E8+F8)/2 -> 9360
A26: Liabilities
A27: Fiscal Year | B27: FY 2021 | C27: FY 2022 | D27: FY 2023 | E27: FY 2024 | F27: FY 2025
A28: Accounts Payable | B28: 7826 | C28: 8434 | D28: 6741 | E28: 6923 | F28: 5484
A29: Accrued Expenses | B29: 2374 | C29: 2054 | D29: 1414 | E29: 1579 | F29: 1671
A30: Short-Term Debt | B30: 248 | C30: 654 | D30: - | E30: - | F30: -
A31: Current Portion of Long-Term Debt | B31: 3677 | C31: 3615 | D31: 2597 | E31: 3200 | F31: 3167
A32: Current Portion of Leases | B32: 334 | C32: 329 | D32: 350 | E32: 340 | F32: 342
A33: Current Income Taxes Payable | B33: 1161 | C33: 995 | D33: 442 | E33: 404 | F33: 213
A34: Current Unearned Revenue | B34: 1021 | C34: 1016 | D34: 853 | E34: 803 | F34: 709
A35: Other Current Liabilities | B35: 3440 | C35: 3343 | D35: 3474 | E35: 3790 | F35: 4825
A36: Total Current Liabilities | B36: 20081 | C36: 20440 | D36: 15871 | E36: 17039 | F36: 16411
A37: Long-Term Debt | B37: 13799 | C37: 15192 | D37: 17101 | E37: 19132 | F37: 18488
A38: Long-Term Leases | B38: 1078 | C38: 1159 | D38: 1299 | E38: 1323 | F38: 1212
A39: Long-Term Unearned Revenue | B39: 218 | C39: 192 | D39: 160 | E39: 217 | F39: 238
A40: Pension & Post-Retirement Benefits | B40: 6160 | C40: 2810 | D40: 2896 | E40: 2403 | F40: 1832
A41: Long-Term Deferred Tax Liabilities | B41: 1499 | C41: 1543 | D41: 1140 | E41: 1005 | F41: 953
A42: Other Long-Term Liabilities | B42: 2467 | C42: 2213 | D42: 2283 | E42: 2413 | F42: 2703
A43: Total Liabilities | B43: 45302 | C43: 43549 | D43: 40750 | E43: 43532 | F43: 41837
A44: Total Debt | B44: =B30+B31+B37 -> 17724 | C44: =C30+C31+C37 -> 19461 | D44: =D31+D37 -> 19698 | E44: =E31+E37 -> 22332 | F44: =F31+F37 -> 21655
A46: Shareholders' Equity
A47: Fiscal Year | B47: FY 2021 | C47: FY 2022 | D47: FY 2023 | E47: FY 2024 | F47: FY 2025
A48: Common Stock | B48: 1176 | C48: 1144 | D48: 1142 | E48: 1142 | F48: 1142
A49: Retained Earnings | B49: 40365 | C49: 35453 | D49: 32517 | E49: 30883 | F49: 29931
A50: Comprehensive Income & Other | B50: -749 | C50: 2976 | D50: 1618 | E50: 3574 | F50: 2121
A51: Total Common Equity | B51: 40792 | C51: 39573 | D51: 35277 | E51: 35599 | F51: 33194
A52: Minority Interest | B52: 1289 | C52: 1350 | D52: 1368 | E52: 1284 | F52: 1143
A53: Shareholders' Equity | B53: 42081 | C53: 40923 | D53: 36645 | E53: 36883 | F53: 34337
A54: Total Liabilities & Equity | B54: 87383 | C54: 84472 | D54: 77395 | E54: 80415 | F54: 76174
A57: Balance Check | B57: =B22-B54 -> 0 | C57: =C22-C54 -> 0 | D57: =D22-D54 -> 0 | E57: =E22-E54 -> 0 | F57: =F22-F54 -> 0

Sheet Cash Flow
A1: BASF — Cash Flow Statement (FY2021–FY2025)
A2: Fiscal Year | B2: FY 2021 | C2: FY 2022 | D2: FY 2023 | E2: FY 2024 | F2: FY 2025
A3: Net Income | B3: ='Income Statement'!B27 -> 5523 | C3: ='Income Statement'!C27 -> -627 | D3: ='Income Statement'!D27 -> 225 | E3: ='Income Statement'!E27 -> 1298 | F3: ='Income Statement'!F27 -> 1619
A4: Depreciation & Amortization | B4: 3518 | C4: 3800 | D4: 3769 | E4: 3647 | F4: 3580
A5: Other Amortization | B5: 25 | C5: 27 | D5: 29 | E5: - | F5: -
A6: Loss (Gain) From Sale of Assets | B6: -611 | C6: -1 | D6: -103 | E6: -57 | F6: -842
A7: Asset Writedown & Restructuring Costs | B7: 144 | C7: 373 | D7: 1143 | E7: 753 | F7: 404
A8: Loss (Gain) on Equity Investments | B8: - | C8: 4499 | D8: 544 | E8: -212 | F8: 276
A9: Other Operating Activities | B9: -1 | C9: 1688 | D9: 5 | E9: 398 | F9: -230
A10: Change in Accounts Receivable | B10: -1272 | C10: 219 | D10: 1443 | E10: 42 | F10: 530
A11: Change in Inventory | B11: -3304 | C11: -1991 | D11: 1896 | E11: 222 | F11: 263
A12: Change in Accounts Payable | B12: - | C12: 451 | D12: -1544 | E12: 96 | F12: -736
A13: Change in Other Net Operating Assets | B13: 3223 | C13: -729 | D13: 704 | E13: 511 | F13: 564
A14: Operating Cash Flow | B14: 7245 | C14: 7709 | D14: 8111 | E14: 6946 | F14: 5610
A15: Operating Cash Flow Growth | B15: 0.3384 | C15: 0.064 | D15: 0.0521 | E15: -0.1436 | F15: -0.1923
A17: Investing Activities
A18: Fiscal Year | B18: FY 2021 | C18: FY 2022 | D18: FY 2023 | E18: FY 2024 | F18: FY 2025
A19: Capital Expenditures | B19: -3532 | C19: -4375 | D19: -5395 | E19: -6198 | F19: -4267
A20: Cash Acquisitions | B20: -600 | C20: -13 | D20: -5 | E20: -202 | F20: -1
A21: Divestitures | B21: 1030 | C21: 691 | D21: 32 | E21: 75 | F21: 871
A22: Investment in Securities | B22: -994 | C22: -1273 | D22: -1063 | E22: 436 | F22: -1121
A23: Other Investing Activities | B23: 1474 | C23: 1192 | D23: 1440 | E23: 808 | F23: 1310
A24: Investing Cash Flow | B24: -2622 | C24: -3778 | D24: -4991 | E24: -5081 | F24: -3208
A26: Financing Activities
A27: Fiscal Year | B27: FY 2021 | C27: FY 2022 | D27: FY 2023 | E27: FY 2024 | F27: FY 2025
A28: Long-Term Debt Issued | B28: 7627 | C28: 10896 | D28: 9503 | E28: 6362 | F28: 6394
A29: Long-Term Debt Repaid | B29: -10772 | C29: -10330 | D29: -9244 | E29: -4579 | F29: -6369
A30: Net Debt Issued (Repaid) | B30: -3145 | C30: 566 | D30: 259 | E30: 1783 | F30: 25
A31: Repurchase of Common Stock | B31: - | C31: -1331 | D31: -70 | E31: -46 | F31: -355
A32: Common Dividends Paid | B32: -3031 | C32: -3072 | D32: -3034 | E32: -3035 | F32: -2086
A33: Other Financing Activities | B33: -281 | C33: -176 | D33: -60 | E33: -249 | F33: -
A34: Financing Cash Flow | B34: -6457 | C34: -4013 | D34: -2905 | E34: -1547 | F34: -2416
A37: Fiscal Year | B37: FY 2021 | C37: FY 2022 | D37: FY 2023 | E37: FY 2024 | F37: FY 2025
A38: Foreign Exchange Rate Adjustments | B38: 131 | C38: -25 | D38: -106 | E38: -21 | F38: -88
A39: Miscellaneous Cash Flow Adjustments | B39: -8 | C39: -1 | D39: - | E39: - | F39: -1
A40: Net Cash Flow | B40: -1711 | C40: -108 | D40: 109 | E40: 297 | F40: -103

Sheet Financial Forecasting
A1: BASF — Financial Forecasting & Scenario Analysis
A3: Historical Income Statement | B3: FY2021 | C3: FY2022 | D3: FY2023 | E3: FY2024 | F3: FY2025
A4: Revenue | B4: ='Income Statement'!B2 -> 78598 | C4: ='Income Statement'!C2 -> 87327 | D4: ='Income Statement'!D2 -> 68902 | E4: ='Income Statement'!E2 -> 61444 | F4: ='Income Statement'!F2 -> 59657
A5: Revenue Growth | C5: =(C4-B4)/B4 -> 0.11105881 | D5: =(D4-C4)/C4 -> -0.21098858 | E5: =(E4-D4)/D4 -> -0.10824069 | F5: =(F4-E4)/E4 -> -0.029083393
A6: Cost of Revenue as a % of Revenue | B6: ='Income Statement'!B4/'Income Statement'!B2 -> 0.75181302 | C6: ='Income Statement'!C4/'Income Statement'!C2 -> 0.76376149 | D6: ='Income Statement'!D4/'Income Statement'!D2 -> 0.76203884 | E6: ='Income Statement'!E4/'Income Statement'!E2 -> 0.75734002 | F6: ='Income Statement'!F4/'Income Statement'!F2 -> 0.76314598
A7: Gross Profit Margin | B7: ='Income Statement'!B5/'Income Statement'!B2 -> 0.24818698 | C7: ='Income Statement'!C5/'Income Statement'!C2 -> 0.23623851 | D7: ='Income Statement'!D5/'Income Statement'!D2 -> 0.23796116 | E7: ='Income Statement'!E5/'Income Statement'!E2 -> 0.24265998 | F7: ='Income Statement'!F5/'Income Statement'!F2 -> 0.23685402
A8: Operating Expense as a % of Revenue | B8: ='Income Statement'!B9/'Income Statement'!B2 -> 0.15318456 | C8: ='Income Statement'!C9/'Income Statement'!C2 -> 0.157729 | D8: ='Income Statement'!D9/'Income Statement'!D2 -> 0.19672869 | E8: ='Income Statement'!E9/'Income Statement'!E2 -> 0.20223293 | F8: ='Income Statement'!F9/'Income Statement'!F2 -> 0.19540037
A9: Operating Profit Margin | B9: ='Income Statement'!B10/'Income Statement'!B2 -> 0.095002417 | C9: ='Income Statement'!C10/'Income Statement'!C2 -> 0.07850951 | D9: ='Income Statement'!D10/'Income Statement'!D2 -> 0.041232475 | E9: ='Income Statement'!E10/'Income Statement'!E2 -> 0.040427056 | F9: ='Income Statement'!F10/'Income Statement'!F2 -> 0.041453643
A10: Net Profit Margin | B10: ='Income Statement'!B27/'Income Statement'!B2 -> 0.070268964 | C10: ='Income Statement'!C27/'Income Statement'!C2 -> -0.00717991 | D10: ='Income Statement'!D27/'Income Statement'!D2 -> 0.0032655075 | E10: ='Income Statement'!E27/'Income Statement'!E2 -> 0.021124927 | F10: ='Income Statement'!F27/'Income Statement'!F2 -> 0.027138475
A11: EBITDA Margin | B11: =('Income Statement'!B10+'Cash Flow'!B4)/'Income Statement'!B2 -> 0.13976183 | C11: =('Income Statement'!C10+'Cash Flow'!C4)/'Income Statement'!C2 -> 0.12202412 | D11: =('Income Statement'!D10+'Cash Flow'!D4)/'Income Statement'!D2 -> 0.095933355 | E11: =('Income Statement'!E10+'Cash Flow'!E4)/'Income Statement'!E2 -> 0.099781915 | F11: =('Income Statement'!F10+'Cash Flow'!F4)/'Income Statement'!F2 -> 0.10146337
A12: Interest Expense as % of Revenue | B12: ='Income Statement'!B11/'Income Statement'!B2 -> -0.0064378228 | C12: ='Income Statement'!C11/'Income Statement'!C2 -> -0.0072257148 | D12: ='Income Statement'!D11/'Income Statement'!D2 -> -0.012597602 | E12: ='Income Statement'!E11/'Income Statement'!E2 -> -0.015119458 | F12: ='Income Statement'!F11/'Income Statement'!F2 -> -0.015488543
A13: Tax Rate | B13: ='Income Statement'!B22/'Income Statement'!B21 -> 0.19199785 | C13: ='Income Statement'!C22/'Income Statement'!C21 -> 1.3285714 | D13: ='Income Statement'!D22/'Income Statement'!D21 -> 0.73309859 | E13: ='Income Statement'!E22/'Income Statement'!E21 -> 0.30789898 | F13: ='Income Statement'!F22/'Income Statement'!F21 -> 0.37050654
A15: Historical Balance Sheet | B15: FY2021 | C15: FY2022 | D15: FY2023 | E15: FY2024 | F15: FY2025
A16: Working Capital | B16: ='Balance Sheet'!B14-'Balance Sheet'!B36 -> 14970 | C16: ='Balance Sheet'!C14-'Balance Sheet'!C36 -> 16982 | D16: ='Balance Sheet'!D14-'Balance Sheet'!D36 -> 15601 | E16: ='Balance Sheet'!E14-'Balance Sheet'!E36 -> 14193 | F16: ='Balance Sheet'!F14-'Balance Sheet'!F36 -> 15273
A17: Working Capital as a percentage of Revenue | B17: =B16/B4 -> 0.19046286 | C17: =C16/C4 -> 0.19446448 | D17: =D16/D4 -> 0.22642304 | E17: =E16/E4 -> 0.23099082 | F17: =F16/F4 -> 0.25601354
A18: Current Ratio | B18: ='Balance Sheet'!B14/'Balance Sheet'!B36 -> 1.7454808 | C18: ='Balance Sheet'!C14/'Balance Sheet'!C36 -> 1.8308219 | D18: ='Balance Sheet'!D14/'Balance Sheet'!D36 -> 1.9829878 | E18: ='Balance Sheet'!E14/'Balance Sheet'!E36 -> 1.8329714 | F18: ='Balance Sheet'!F14/'Balance Sheet'!F36 -> 1.9306563
A19: Quick Ratio | B19: =('Balance Sheet'!B14-'Balance Sheet'!B11)/'Balance Sheet'!B36 -> 1.0548777 | C19: =('Balance Sheet'!C14-'Balance Sheet'!C11)/'Balance Sheet'!C36 -> 1.0466732 | D19: =('Balance Sheet'!D14-'Balance Sheet'!D11)/'Balance Sheet'!D36 -> 1.1086888 | E19: =('Balance Sheet'!E14-'Balance Sheet'!E11)/'Balance Sheet'!E36 -> 1.0300487 | F19: =('Balance Sheet'!F14-'Balance Sheet'!F11)/'Balance Sheet'!F36 -> 1.1892024
A20: Cash Ratio | B20: ='Balance Sheet'!B3/'Balance Sheet'!B36 -> 0.13067078 | C20: ='Balance Sheet'!C3/'Balance Sheet'!C36 -> 0.12309198 | D20: ='Balance Sheet'!D3/'Balance Sheet'!D36 -> 0.165333 | E20: ='Balance Sheet'!E3/'Balance Sheet'!E36 -> 0.17101943 | F20: ='Balance Sheet'!F3/'Balance Sheet'!F36 -> 0.16269575
A21: Total Debt | B21: ='Balance Sheet'!B44 -> 17724 | C21: ='Balance Sheet'!C44 -> 19461 | D21: ='Balance Sheet'!D44 -> 19698 | E21: ='Balance Sheet'!E44 -> 22332 | F21: ='Balance Sheet'!F44 -> 21655
A22: Debt to Equity Ratio | B22: =B21/'Balance Sheet'!B53 -> 0.42118771 | C22: =C21/'Balance Sheet'!C53 -> 0.47555165 | D22: =D21/'Balance Sheet'!D53 -> 0.53753582 | E22: =E21/'Balance Sheet'!E53 -> 0.6054822 | F22: =F21/'Balance Sheet'!F53 -> 0.6306608
A23: Debt to Asset Ratio | B23: ='Financial Forecasting'!B21/'Balance Sheet'!B22 -> 0.20283121 | C23: =C21/'Balance Sheet'!C22 -> 0.23038403 | D23: =D21/'Balance Sheet'!D22 -> 0.25451257 | E23: =E21/'Balance Sheet'!E22 -> 0.27770938 | F23: ='Financial Forecasting'!F21/'Balance Sheet'!F22 -> 0.28428335
A24: Equity Ratio | B24: ='Balance Sheet'!B53/'Balance Sheet'!B22 -> 0.48156964 | C24: ='Balance Sheet'!C53/'Balance Sheet'!C22 -> 0.48445639 | D24: ='Balance Sheet'!D53/'Balance Sheet'!D22 -> 0.4734802 | E24: ='Balance Sheet'!E53/'Balance Sheet'!E22 -> 0.45865821 | F24: ='Balance Sheet'!F53/'Balance Sheet'!F22 -> 0.4507706
A25: Net Debt | B25: ='Financial Forecasting'!B21-'Balance Sheet'!B3 -> 15100 | C25: =C21-'Balance Sheet'!C3 -> 16945 | D25: ='Financial Forecasting'!D21-'Balance Sheet'!D3 -> 17074 | E25: ='Financial Forecasting'!E21-'Balance Sheet'!E3 -> 19418 | F25: =F21-'Balance Sheet'!F3 -> 18985
A26: EBITDA | B26: ='Income Statement'!B10+'Cash Flow'!B4 -> 10985 | C26: ='Income Statement'!C10+'Cash Flow'!C4 -> 10656 | D26: ='Income Statement'!D10+'Cash Flow'!D4 -> 6610 | E26: ='Income Statement'!E10+'Cash Flow'!E4 -> 6131 | F26: ='Income Statement'!F10+'Cash Flow'!F4 -> 6053
A27: Net Debt-to-EBITDA | B27: =B25/B26 -> 1.3746017 | C27: =C25/C26 -> 1.5901839 | D27: =D25/D26 -> 2.583056 | E27: =E25/E26 -> 3.1671832 | F27: =F25/F26 -> 3.1364613
A29: Historical Cash Flow Statement | B29: FY2021 | C29: FY2022 | D29: FY2023 | E29: FY2024 | F29: FY2025
A30: Operating Cash Flow Margin | B30: ='Cash Flow'!B14/'Income Statement'!B2 -> 0.092177918 | C30: ='Cash Flow'!C14/'Income Statement'!C2 -> 0.088277394 | D30: ='Cash Flow'!D14/'Income Statement'!D2 -> 0.11771792 | E30: ='Cash Flow'!E14/'Income Statement'!E2 -> 0.11304603 | F30: ='Cash Flow'!F14/'Income Statement'!F2 -> 0.094037582
A31: Free Cash Flow | B31: ='Cash Flow'!B14+'Cash Flow'!B19 -> 3713 | C31: ='Cash Flow'!C14+'Cash Flow'!C19 -> 3334 | D31: ='Cash Flow'!D14+'Cash Flow'!D19 -> 2716 | E31: ='Cash Flow'!E14+'Cash Flow'!E19 -> 748 | F31: ='Cash Flow'!F14+'Cash Flow'!F19 -> 1343
A32: Operating Cash Flow to Total Debt | B32: ='Cash Flow'!B14/'Financial Forecasting'!B21 -> 0.40876777 | C32: ='Cash Flow'!C14/'Financial Forecasting'!C21 -> 0.39612558 | D32: ='Cash Flow'!D14/'Financial Forecasting'!D21 -> 0.41176769 | E32: ='Cash Flow'!E14/'Financial Forecasting'!E21 -> 0.31103349 | F32: ='Cash Flow'!F14/'Financial Forecasting'!F21 -> 0.25906257
A33: Cash Flow to Interest Coverage | B33: ='Cash Flow'!B14/ABS('Income Statement'!B11) -> 14.318182 | C33: ='Cash Flow'!C14/ABS('Income Statement'!C11) -> 12.217116 | D33: ='Cash Flow'!D14/ABS('Income Statement'!D11) -> 9.34447 | E33: ='Cash Flow'!E14/ABS('Income Statement'!E11) -> 7.4768568 | F33: ='Cash Flow'!F14/ABS('Income Statement'!F11) -> 6.0714286
A34: Depreciation & Amortization | B34: ='Cash Flow'!B4 -> 3518 | C34: ='Cash Flow'!C4 -> 3800 | D34: ='Cash Flow'!D4 -> 3769 | E34: ='Cash Flow'!E4 -> 3647 | F34: ='Cash Flow'!F4 -> 3580
A35: D & A % of Revenue | B35: =B34/B4 -> 0.044759409 | C35: =C34/C4 -> 0.043514606 | D35: =D34/D4 -> 0.05470088 | E35: =E34/E4 -> 0.05935486 | F35: =F34/F4 -> 0.060009722
A36: CapEx % of Revenue | B36: ='Cash Flow'!B19/'Financial Forecasting'!B4 -> -0.04493753 | C36: ='Cash Flow'!C19/'Financial Forecasting'!C4 -> -0.050099053 | D36: ='Cash Flow'!D19/'Financial Forecasting'!D4 -> -0.078299614 | E36: ='Cash Flow'!E19/'Financial Forecasting'!E4 -> -0.10087234 | F36: ='Cash Flow'!F19/'Financial Forecasting'!F4 -> -0.071525554
A37: Current Asset % of Revenue | B37: ='Balance Sheet'!B14/'Financial Forecasting'!B4 -> 0.44595282 | C37: ='Balance Sheet'!C14/'Financial Forecasting'!C4 -> 0.42852726 | D37: ='Balance Sheet'!D14/'Financial Forecasting'!D4 -> 0.45676468 | E37: ='Balance Sheet'!E14/'Financial Forecasting'!E4 -> 0.50830024 | F37: ='Balance Sheet'!F14/'Financial Forecasting'!F4 -> 0.5311028
A38: Current Liabilities % Revenue | B38: ='Balance Sheet'!B36/'Financial Forecasting'!B4 -> 0.25548996 | C38: ='Balance Sheet'!C36/'Financial Forecasting'!C4 -> 0.23406278 | D38: ='Balance Sheet'!D36/'Financial Forecasting'!D4 -> 0.23034164 | E38: ='Balance Sheet'!E36/'Financial Forecasting'!E4 -> 0.27730942 | F38: ='Balance Sheet'!F36/'Financial Forecasting'!F4 -> 0.27508926
A40: Historical Working Capital Analysis | B40: FY2021 | C40: FY2022 | D40: FY2023 | E40: FY2024 | F40: FY2025
A41: Days Inventory Outstanding (DIO) | B41: ='Balance Sheet'!B11/'Income Statement'!B4*365 -> 85.661437 | C41: ='Balance Sheet'!C11/'Income Statement'!C4*365 -> 87.71339 | D41: ='Balance Sheet'!D11/'Income Statement'!D4*365 -> 96.460214 | E41: ='Balance Sheet'!E11/'Income Statement'!E4*365 -> 107.31003 | F41: ='Balance Sheet'!F11/'Income Statement'!F4*365 -> 97.55354
A42: Days Sales Outstanding (DSO) | B42: ='Balance Sheet'!B8/'Income Statement'!B2*365 -> 55.475839 | C42: ='Balance Sheet'!C8/'Income Statement'!C2*365 -> 50.394552 | D42: ='Balance Sheet'!D8/'Income Statement'!D2*365 -> 55.182796 | E42: ='Balance Sheet'!E8/'Income Statement'!E2*365 -> 61.738249 | F42: ='Balance Sheet'!F8/'Income Statement'!F2*365 -> 50.947165
A43: Days Payables Outstanding (DPO) | B43: ='Balance Sheet'!B28/'Income Statement'!B4*365 -> 48.340526 | C43: ='Balance Sheet'!C28/'Income Statement'!C4*365 -> 46.155149 | D43: ='Balance Sheet'!D28/'Income Statement'!D4*365 -> 46.860644 | E43: ='Balance Sheet'!E28/'Income Statement'!E4*365 -> 54.302123 | F43: ='Balance Sheet'!F28/'Income Statement'!F4*365 -> 43.966437
A44: Cash Conversion Cycle | B44: =B41+B42-B43 -> 92.796751 | C44: =C41+C42-C43 -> 91.952793 | D44: =D41+D42-D43 -> 104.78237 | E44: =E41+E42-E43 -> 114.74616 | F44: =F41+F42-F43 -> 104.53427
A46: Historical Non-Current Assets & Liabilities | B46: FY2021 | C46: FY2022 | D46: FY2023 | E46: FY2024 | F46: FY2025
A47: Non-Current Assets | B47: ='Balance Sheet'!B22-'Balance Sheet'!B14 -> 52332 | C47: ='Balance Sheet'!C22-'Balance Sheet'!C14 -> 47050 | D47: ='Balance Sheet'!D22-'Balance Sheet'!D14 -> 45923 | E47: ='Balance Sheet'!E22-'Balance Sheet'!E14 -> 49183 | F47: ='Balance Sheet'!F22-'Balance Sheet'!F14 -> 44490
A48: Non-Current Assets as % of Revenue | B48: =B47/B4 -> 0.66581847 | C48: =C47/C4 -> 0.53877953 | D48: =D47/D4 -> 0.66649734 | E48: =E47/E4 -> 0.80045244 | F48: =F47/F4 -> 0.74576328
A49: Non-Current Liabilities | B49: ='Balance Sheet'!B43-'Balance Sheet'!B36 -> 25221 | C49: ='Balance Sheet'!C43-'Balance Sheet'!C36 -> 23109 | D49: ='Balance Sheet'!D43-'Balance Sheet'!D36 -> 24879 | E49: ='Balance Sheet'!E43-'Balance Sheet'!E36 -> 26493 | F49: ='Balance Sheet'!F43-'Balance Sheet'!F36 -> 25426
A50: Non-Current Liabilities as a percentage of Revenue | B50: =B49/B4 -> 0.32088603 | C50: =C49/C4 -> 0.26462606 | D50: =D49/D4 -> 0.36107805 | E50: =E49/E4 -> 0.4311731 | F50: =F49/F4 -> 0.42620313
A51: Debt to Revenue Ratio | B51: ='Balance Sheet'!B44/'Financial Forecasting'!B4 -> 0.22550192 | C51: ='Balance Sheet'!C44/'Financial Forecasting'!C4 -> 0.22285204 | D51: ='Balance Sheet'!D44/'Financial Forecasting'!D4 -> 0.2858843 | E51: ='Balance Sheet'!E44/'Financial Forecasting'!E4 -> 0.3634529 | F51: ='Balance Sheet'!F44/'Financial Forecasting'!F4 -> 0.36299177
A52: Change in Debt | C52: =C21-B21 -> 1737 | D52: =D21-C21 -> 237 | E52: =E21-D21 -> 2634 | F52: =F21-E21 -> -677
A54: Income Statement Forecast | B54: FY2025A | C54: FY2026F | D54: FY2027F | E54: FY2028F
A55: Revenue Growth Assumption | B55: — | C55: 0.06 | D55: 0.04 | E55: 0.03
A56: Revenue (€m) | B56: =F4 -> 59657 | C56: =B56*(1+C55) -> 63236.42 | D56: =C56*(1+D55) -> 65765.877 | E56: =D56*(1+E55) -> 67738.853
A57: Cost of Revenue (€m) | C57: =$B$80*C56 -> 48035.641 | D57: =$B$80*D56 -> 49957.067 | E57: =$B$80*E56 -> 51455.779
A58: Operating Expense | C58: =$B$83*C56 -> 11449.277 | D58: =$B$83*D56 -> 11907.248 | E58: =$B$83*E56 -> 12264.465
A59: Operating Profit | C59: =C56-C57-C58 -> 3751.5019 | D59: =D56-D57-D58 -> 3901.562 | E59: =E56-E57-E58 -> 4018.6088
A60: Operating Profit Margin | C60: =C59/C56 -> 0.05932502 | D60: =D59/D56 -> 0.05932502 | E60: =E59/E56 -> 0.05932502
A61: Interest Expense | C61: =$B$86*C56 -> -719.24018 | D61: =$B$86*D56 -> -748.00979 | E61: =$B$86*E56 -> -770.45008
A62: Pre-Tax Income | C62: =C59+C61 -> 3032.2617 | D62: =D59+D61 -> 3153.5522 | E62: =E59+E61 -> 3248.1588
A63: Tax Rate | C63: =F13 -> 0.37050654 | D63: =F13 -> 0.37050654 | E63: =F13 -> 0.37050654
A64: Income Tax Expense | C64: =C62*C63 -> 1123.4728 | D64: =D62*D63 -> 1168.4117 | E64: =E62*E63 -> 1203.464
A65: Net Income | C65: =C62-C64 -> 1908.7889 | D65: =D62-D64 -> 1985.1405 | E65: =E62-E64 -> 2044.6947
A66: Net Profit Margin | C66: =C65/C56 -> 0.030184962 | D66: =D65/D56 -> 0.030184962 | E66: =E65/E56 -> 0.030184962
A68: Financial Assumptions & Drivers
A70: Revenue Compound Annual Growth Rate (CAGR) | B70: =('Income Statement'!F2/'Income Statement'!B2)^(1/4)-1 -> -0.066611429
A72: Revenue Growth | B72: FY2024 | C72: FY2025 | D72: Average
B73: =E76-D76 -> 0.10274789 | C73: =F76-E76 -> 0.079157297 | D73: =AVERAGE(B73,C73) -> 0.090952595
A75: Recent growth trend | B75: FY2021 | C75: FY2022 | D75: FY2023 | E75: FY2024 | F75: FY2025
C76: =C5 -> 0.11105881 | D76: =D5 -> -0.21098858 | E76: =E5 -> -0.10824069 | F76: =F5 -> -0.029083393
A77: FY2026 Historical Trend Growth
A78: =F76+D73 -> 0.061869202
A80: Cost of Revenue Average (% of Revenue) | B80: =AVERAGE(B6:F6) -> 0.75961987
A81: =AVERAGE(B6,C6,D6,E6,F6) -> 0.75961987
A83: Average Operating Expense (% of Revenue) | B83: =AVERAGE(B8:F8) -> 0.18105511
A84: =AVERAGE(B8,C8,D8,E8,F8) -> 0.18105511
A86: Historical Average Interest Expense (% of Revenue) | B86: =AVERAGE(B12:F12) -> -0.011373828
A87: =AVERAGE(B12,C12,D12,E12,F12) -> -0.011373828
A89: Balance Sheet Forecast | B89: FY2025A | C89: FY2026F | D89: FY2027F | E89: FY2028F
A90: Assets
A91: Cash & Cash Equivalents (€m) | B91: ='Balance Sheet'!F3 -> 2670 | C91: =C159 -> 776.65351 | D91: =D159 -> -1048.0068 | E91: =E159 -> -2708.1027
A92: Accounts Receivable (€m) | B92: ='Balance Sheet'!F8 -> 8327 | C92: =C56*$B$130/365 -> 9485.068 | D92: =D56*$B$130/365 -> 9864.4707 | E92: =E56*$B$130/365 -> 10160.405
A93: Inventory (€m) | B93: ='Balance Sheet'!F11 -> 12168 | C93: =C57*$B$131/365 -> 12494.494 | D93: =D57*$B$131/365 -> 12994.274 | E93: =E57*$B$131/365 -> 13384.102
A94: Other Current Assets (€m) | B94: ='Balance Sheet'!F14-'Balance Sheet'!F3-'Balance Sheet'!F8-'Balance Sheet'!F11 -> 8519 | C94: =$B$133 -> 8519 | D94: =$B$133 -> 8519 | E94: =$B$133 -> 8519
A95: Total Current Assets (€m) | B95: =SUM(B91:B94) -> 31684 | C95: =SUM(C91:C94) -> 31275.216 | D95: =SUM(D91:D94) -> 30329.738 | E95: =SUM(E91:E94) -> 29355.405
A96: Net Non-Current Assets / PP&E (€m) | B96: ='Balance Sheet'!F22-'Balance Sheet'!F14 -> 44490 | C96: =B96-C150-C143 -> 45544.715 | D96: =C96-D150-D143 -> 46641.619 | E96: =D96-E150-E143 -> 47771.43
A97: Total Assets (€m) | B97: =B95+B96 -> 76174 | C97: =C95+C96 -> 76819.931 | D97: =D95+D96 -> 76971.357 | E97: =E95+E96 -> 77126.835
A99: Liabilities & Equity
A100: Accounts Payable (€m) | B100: ='Balance Sheet'!F28 -> 5484 | C100: =C57*$B$132/365 -> 6307.1423 | D100: =D57*$B$132/365 -> 6559.428 | E100: =E57*$B$132/365 -> 6756.2109
A101: Other Current Liabilities (€m) | B101: ='Balance Sheet'!F36-'Balance Sheet'!F28-N('Balance Sheet'!F30)-'Balance Sheet'!F31 -> 7760 | C101: =$B$134 -> 7760 | D101: =$B$134 -> 7760 | E101: =$B$134 -> 7760
A102: Total Current Liabilities (€m) | B102: =SUM(B100:B101) -> 13244 | C102: =SUM(C100:C101) -> 14067.142 | D102: =SUM(D100:D101) -> 14319.428 | E102: =SUM(E100:E101) -> 14516.211
A103: Total Debt (€m) | B103: ='Balance Sheet'!F44 -> 21655 | C103: =$B$136 -> 21655 | D103: =$B$136 -> 21655 | E103: =$B$136 -> 21655
A104: Other Non-Current Liabilities (€m) | B104: ='Balance Sheet'!F43-'Balance Sheet'!F36-'Balance Sheet'!F37 -> 6938 | C104: =$B$135 -> 6938 | D104: =$B$135 -> 6938 | E104: =$B$135 -> 6938
A105: Total Liabilities (€m) | B105: =B102+B103+B104 -> 41837 | C105: =C102+C103+C104 -> 42660.142 | D105: =D102+D103+D104 -> 42912.428 | E105: =E102+E103+E104 -> 43109.211
A106: Ending Shareholders' Equity (€m) | B106: ='Balance Sheet'!F53 -> 34337 | C106: =B106+C142-C107 -> 34159.789 | D106: =C106+D142-D107 -> 34058.929 | E106: =D106+E142-E107 -> 34017.624
A107: Dividends Paid (€m) | C107: =$B$139 -> 2086 | D107: =$B$139 -> 2086 | E107: =$B$139 -> 2086
A108: Debt Issuance / (Repayment) (€m) | C108: =C103-B103 -> 0 | D108: =D103-C103 -> 0 | E108: =E103-D103 -> 0
A109: Balance Check (Total Assets − Total Liabilities − Equity) | C109: =C97-C105-C106 -> 0 | D109: =D97-D105-D106 -> 0 | E109: =E97-E105-E106 -> 0
A111: Liquidity & Working Capital Ratios
A112: Working Capital (€m) | B112: =B95-B102 -> 18440 | C112: =C95-C102 -> 17208.074 | D112: =D95-D102 -> 16010.31 | E112: =E95-E102 -> 14839.194
A113: Current Ratio (x) | B113: =B95/B102 -> 2.3923286 | C113: =C95/C102 -> 2.2232814 | D113: =D95/D102 -> 2.1180831 | E113: =E95/E102 -> 2.0222498
A114: Quick Ratio (x) | B114: =(B95-B93)/B102 -> 1.4735729 | C114: =(C95-C93)/C102 -> 1.3350772 | D114: =(D95-D93)/D102 -> 1.2106254 | E114: =(E95-E93)/E102 -> 1.1002391
A115: Cash Ratio (x) | B115: =B91/B102 -> 0.20160072 | C115: =C91/C102 -> 0.055210468 | D115: =D91/D102 -> -0.073187755 | E115: =E91/E102 -> -0.18655713
A116: DIO (days) | B116: =B41 -> 85.661437 | C116: =$B$131 -> 94.939723 | D116: =$B$131 -> 94.939723 | E116: =$B$131 -> 94.939723
...
